flask_shortcut/__init__.py
flask_shortcut/shortcut.py
flask_shortcut/util.py
flask_shortcut-0.4.1.dist-info/LICENSE
flask_shortcut-0.4.1.dist-info/WHEEL
flask_shortcut-0.4.1.dist-info/METADATA
flask_shortcut-0.4.1.dist-info/RECORD
